README.md
setup.py
probe/__init__.py
probe/application.py
probe/buildinfo.py
probe/cli.py
probe/controller.py
probe/model.py
probe/monitor.py
probe/testing.py
probe/migrations/README
probe/migrations/alembic.ini
probe/migrations/env.py
probe/migrations/script.py.mako
probe/migrations/versions/5edecbbc06f1_add_executions.py
probe/migrations/versions/6cecd2318b0e_initialtablelayout.py
probe/static/bundle.js
probe/static/main.css
probe/static/probe.png
probe/static/fa/css/font-awesome.css
probe/static/fa/css/font-awesome.css.map
probe/static/fa/css/font-awesome.min.css
probe/static/fa/fonts/FontAwesome.otf
probe/static/fa/fonts/fontawesome-webfont.eot
probe/static/fa/fonts/fontawesome-webfont.svg
probe/static/fa/fonts/fontawesome-webfont.ttf
probe/static/fa/fonts/fontawesome-webfont.woff
probe/static/fa/fonts/fontawesome-webfont.woff2
probe/static/script/api.ts
probe/static/script/main.ts
probe/static/script/model.ts
probe/static/script/components/app.tsx
probe/static/script/components/button.tsx
probe/static/script/components/event.tsx
probe/static/script/components/eventlist.tsx
probe/static/script/components/filterinput.tsx
probe/templates/app.html
probe/templates/base.html
probe/templates/login.html
probe/templates/webhook.html
probe_lib.egg-info/PKG-INFO
probe_lib.egg-info/SOURCES.txt
probe_lib.egg-info/dependency_links.txt
probe_lib.egg-info/requires.txt
probe_lib.egg-info/top_level.txt