Metadata-Version: 1.0
Name: probe-lib
Version: 0.1
Summary: Beep? Boop? Beepboop!
Home-page: https://triplet-gmbh.de/
Author: Philipp Benjamin Koeppchen
Author-email: info@triplet-gmbh.de
License: UNKNOWN
Platform: UNKNOWN
